CHANGES.txt
LICENSE.txt
MANIFEST.in
README.txt
seqPlot.py
setup.py
seqPlot.egg-info/PKG-INFO
seqPlot.egg-info/SOURCES.txt
seqPlot.egg-info/dependency_links.txt
seqPlot.egg-info/requires.txt
seqPlot.egg-info/top_level.txt
seqplot/__init__.py
seqplot/seqplot_helpers.py
seqplot/seqplot_main.py