Metadata-Version: 1.1
Name: seqPlot
Version: 0.1.0
Summary: Visualize (multiple) sequence alignment (MSA) with colored boxes
Home-page: https://pypi.python.org/pypi/seqPlot/
Author: Janina Mass
Author-email: janina.mass@hhu.de
License: GPLv3
Platform: UNKNOWN
Classifier: Programming Language :: Python :: 2.7
Classifier: Topic :: Scientific/Engineering :: Bio-Informatics
